setup.cfg
setup.py
requests_debug/__init__.py
requests_debug/debug.py
requests_debug.egg-info/PKG-INFO
requests_debug.egg-info/SOURCES.txt
requests_debug.egg-info/dependency_links.txt
requests_debug.egg-info/requires.txt
requests_debug.egg-info/top_level.txt