Metadata-Version: 1.0
Name: requests-debug
Version: 0.2
Summary: Adds logging and timing for the requests library
Home-page: https://github.com/ericmoritz/requests_debug
Author: Eric Moritz
Author-email: eric@themoritzfamily.com
License: UNKNOWN
Platform: UNKNOWN
